nb_extension_tagstyler-0.0.2.data/data/etc/jupyter/nbconfig/notebook.d/tagstyler.json
nb_extension_tagstyler-0.0.2.data/data/share/jupyter/nbextensions/tagstyler/index.js
nb_extension_tagstyler-0.0.2.data/data/share/jupyter/nbextensions/tagstyler/tagstyler.yaml
tagstyler/__init__.py
tagstyler/static/index.js
tagstyler/static/tagstyler.yaml
nb_extension_tagstyler-0.0.2.dist-info/LICENSE
nb_extension_tagstyler-0.0.2.dist-info/METADATA
nb_extension_tagstyler-0.0.2.dist-info/WHEEL
nb_extension_tagstyler-0.0.2.dist-info/top_level.txt
nb_extension_tagstyler-0.0.2.dist-info/RECORD
