Metadata-Version: 2.1
Name: nb-extension-tagstyler
Version: 0.0.2
Summary: Style classic notebook cells according to simple bootstrap style cell tags.
Home-page: UNKNOWN
License: UNKNOWN
Platform: UNKNOWN
License-File: LICENSE
Requires-Dist: notebook
